[
    {
    "Name": "Sanju Samson",
    "ImgURL": "https://bcciplayerimages.s3.ap-south-1.amazonaws.com/ipl/IPLHeadshot2022/258.png",
    "Team": "RR",
    "Type": "Wicket-Keeper ",
    "Born": "November 11, 1994 Pulluvila, Vizhinjam, Trivandrum",
    "Age": "27 Years, 4 Months, 4 Days",
    "National_Side": "India",
    "Batting_Style": "Right Handed",
    "Bowling": "",
    "MatchPlayed": 121,
    "InningsBatted": 117,
    "NotOuts": 12,
    "RunsScored": 3068,
    "HighestInnScore": "119 v PBKS",
    "Hundreds": 3,
    "Fifties": 15,
    "Fours": 236,
    "Sixes": 132,
    "BattingAVG": 29.21,
    "BattingSR": 134.2,
    "CatchesTaken": 59,
    "StumpingsMade": 10,
    "Ducks": 8,
    "InningsBowled": null,
    "Overs": null,
    "Maidens": null,
    "RunsConceded": null,
    "Wickets": null,
    "Best": "",
    "Three_Wicket_haul": null,
    "Five_Wicket_haul": null,
    "BowlingAVG": null,
    "EconomyRate": null,
    "BowlingSR": null,
    "MatchedPlayed": null
  }
]